[
  {
    "id": "博客建站庆祝文章",
    "title": "个人博客建站庆祝 - 项目功能介绍与使用指南",
    "date": "2024-12-18",
    "category": "项目介绍",
    "tags": [
      "Vue",
      "博客",
      "前端开发",
      "项目搭建"
    ],
    "description": "庆祝个人博客网站成功上线，详细介绍项目功能和使用方法"
  },
  {
    "id": "sample4",
    "title": "React Hooks 使用指南",
    "date": "2023-08-05",
    "category": "前端开发",
    "tags": [
      "React",
      "JavaScript",
      "框架"
    ],
    "description": "详细介绍 React Hooks 的使用方法和最佳实践"
  },
  {
    "id": "sample3",
    "title": "Node.js 性能优化",
    "date": "2023-07-10",
    "category": "后端开发",
    "tags": [
      "Node.js",
      "性能",
      "服务器"
    ],
    "description": "分享 Node.js 应用性能优化的实用技巧"
  },
  {
    "id": "sample2",
    "title": "TypeScript 最佳实践",
    "date": "2023-06-20",
    "category": "编程语言",
    "tags": [
      "TypeScript",
      "JavaScript",
      "开发"
    ],
    "description": "探讨 TypeScript 在项目中的最佳实践方法"
  }
]